moduleultra/__init__.py
moduleultra/errors.py
moduleultra/module_ultra_config.py
moduleultra/module_ultra_repo.py
moduleultra/pipeline_config_utils.py
moduleultra/pipeline_instance.py
moduleultra/pipeline_instance_snakemake_utils.py
moduleultra/pipeline_instance_utils.py
moduleultra/result_schema.py
moduleultra/snakemake_log_handler.py
moduleultra/snakemake_rule_builder.py
moduleultra/snakemake_utils.py
moduleultra/utils.py
moduleultra/version.py
moduleultra/cli/__init__.py
moduleultra/cli/cli.py
moduleultra/cli/daemon.py
moduleultra/daemon/__init__.py
moduleultra/daemon/api.py
moduleultra/daemon/config.py
moduleultra/installation/__init__.py
moduleultra/installation/pipeline_config_utils.py
moduleultra/installation/pipeline_setup.py
ModuleUltra-0.4.1.dist-info/LICENSE
ModuleUltra-0.4.1.dist-info/METADATA
ModuleUltra-0.4.1.dist-info/WHEEL
ModuleUltra-0.4.1.dist-info/dependency_links.txt
ModuleUltra-0.4.1.dist-info/entry_points.txt
ModuleUltra-0.4.1.dist-info/top_level.txt
ModuleUltra-0.4.1.dist-info/RECORD
