Metadata-Version: 2.1
Name: ModuleUltra
Version: 0.4.1
Summary: Tools to make pipelines easier to run and distribute for large biological datasets
Home-page: https://github.com/dcdanko/ModuleUltra
Author: David C Danko
Author-email: dcd3001@med.cornell.edu
License: UNKNOWN
Platform: UNKNOWN
Classifier: Development Status :: 2 - Pre-Alpha
Classifier: Programming Language :: Python :: 3.6
Requires-Dist: click (>=6.7)
Requires-Dist: snakemake (~=4.1.0)
Requires-Dist: PyYAML (~=3.12.0)
Requires-Dist: blessings (~=1.7.0)
Requires-Dist: yaml-backed-structs (~=1.0.0)
Requires-Dist: datasuper (~=0.10.0)
Requires-Dist: gimme-input (==1.0.0)
Requires-Dist: PackageMega (>=0.1.0)
